LICENSE
README.md
setup.py
pyvar/__init__.py
pyvar/config.py
pyvar.egg-info/PKG-INFO
pyvar.egg-info/SOURCES.txt
pyvar.egg-info/dependency_links.txt
pyvar.egg-info/not-zip-safe
pyvar.egg-info/top_level.txt
pyvar/cm/__init__.py
pyvar/cm/core.py
pyvar/cm/utils/__init__.py
pyvar/cm/utils/config.py
pyvar/cm/utils/helper.py
pyvar/ml/__init__.py
pyvar/ml/config.py
pyvar/ml/engines/__init__.py
pyvar/ml/engines/ethosu.py
pyvar/ml/engines/tflite.py
pyvar/ml/utils/__init__.py
pyvar/ml/utils/config.py
pyvar/ml/utils/framerate.py
pyvar/ml/utils/label.py
pyvar/ml/utils/overlay.py
pyvar/ml/utils/resizer.py
pyvar/ml/utils/retriever_https.py
pyvar/ml/utils/timer.py
pyvar/multimedia/__init__.py
pyvar/multimedia/config.py
pyvar/multimedia/helper.py