Metadata-Version: 2.1
Name: pyvar
Version: 1.2.1
Summary: Variscite Python Package
Home-page: https://github.com/varigit/pyvar
Author: Diego Dorta
Author-email: diego.d@variscite.com
License: BDS-3-Clause
Keywords: variscite,ai,ml,API
Classifier: Development Status :: 1 - Planning
Classifier: Intended Audience :: Information Technology
Classifier: Natural Language :: English
Classifier: Operating System :: Other OS
Classifier: Programming Language :: Python :: 3.7
License-File: LICENSE
